pyconturb/__init__.py
pyconturb/_hawcres_io.py
pyconturb/_utils.py
pyconturb/_version.py
pyconturb/coherence.py
pyconturb/core.py
pyconturb/io.py
pyconturb/magnitudes.py
pyconturb/sig_models.py
pyconturb/simulation.py
pyconturb/spectral_models.py
pyconturb/wind_profiles.py
pyconturb-2.7.4.dist-info/LICENSE
pyconturb-2.7.4.dist-info/METADATA
pyconturb-2.7.4.dist-info/WHEEL
pyconturb-2.7.4.dist-info/top_level.txt
pyconturb-2.7.4.dist-info/RECORD
