Metadata-Version: 2.1
Name: pyconturb
Version: 2.7.4
Summary: An open-source constrained turbulence generator
Home-page: https://gitlab.windenergy.dtu.dk/pyconturb/pyconturb
Author: Jenni Rinker
Author-email: rink@dtu.dk
License: MIT
License-File: LICENSE
Requires-Dist: h5py
Requires-Dist: numpy
Requires-Dist: pandas
Requires-Dist: scipy
